{ "frames": [
   {
    "filename": "switcher 0.aseprite",
    "frame": { "x": 0, "y": 0, "w": 48, "h": 32 },
    "rotated": false,
    "trimmed": false,
    "spriteSourceSize": { "x": 0, "y": 0, "w": 48, "h": 32 },
    "sourceSize": { "w": 48, "h": 32 },
    "duration": 100
   },
   {
    "filename": "switcher 1.aseprite",
    "frame": { "x": 50, "y": 0, "w": 48, "h": 32 },
    "rotated": false,
    "trimmed": false,
    "spriteSourceSize": { "x": 0, "y": 0, "w": 48, "h": 32 },
    "sourceSize": { "w": 48, "h": 32 },
    "duration": 100
   },
   {
    "filename": "switcher 2.aseprite",
    "frame": { "x": 100, "y": 0, "w": 48, "h": 32 },
    "rotated": false,
    "trimmed": false,
    "spriteSourceSize": { "x": 0, "y": 0, "w": 48, "h": 32 },
    "sourceSize": { "w": 48, "h": 32 },
    "duration": 100
   },
   {
    "filename": "switcher 3.aseprite",
    "frame": { "x": 0, "y": 34, "w": 48, "h": 32 },
    "rotated": false,
    "trimmed": false,
    "spriteSourceSize": { "x": 0, "y": 0, "w": 48, "h": 32 },
    "sourceSize": { "w": 48, "h": 32 },
    "duration": 100
   },
   {
    "filename": "switcher 4.aseprite",
    "frame": { "x": 50, "y": 34, "w": 48, "h": 32 },
    "rotated": false,
    "trimmed": false,
    "spriteSourceSize": { "x": 0, "y": 0, "w": 48, "h": 32 },
    "sourceSize": { "w": 48, "h": 32 },
    "duration": 100
   },
   {
    "filename": "switcher 5.aseprite",
    "frame": { "x": 100, "y": 34, "w": 48, "h": 32 },
    "rotated": false,
    "trimmed": false,
    "spriteSourceSize": { "x": 0, "y": 0, "w": 48, "h": 32 },
    "sourceSize": { "w": 48, "h": 32 },
    "duration": 100
   }
 ],
 "meta": {
  "app": "https://www.aseprite.org/",
  "version": "1.3.17-arm64",
  "image": "switcher.png",
  "format": "RGBA8888",
  "size": { "w": 148, "h": 66 },
  "scale": "1",
  "frameTags": [
   { "name": "on", "from": 1, "to": 5, "direction": "forward", "color": "#000000ff" }
  ],
  "slices": [
  ]
 }
}
